air_init_mcp/__init__.py
air_init_mcp/__main__.py
air_init_mcp/air_init_mcp.py
air_init_mcp/cli.py
air_init_mcp/utils.py
air_init_mcp-0.1.0.dist-info/licenses/LICENSE
air_init_mcp-0.1.0.dist-info/METADATA
air_init_mcp-0.1.0.dist-info/WHEEL
air_init_mcp-0.1.0.dist-info/entry_points.txt
air_init_mcp-0.1.0.dist-info/top_level.txt
air_init_mcp-0.1.0.dist-info/RECORD
